opal_fetcher_test_dynamoDB/__init__.py
opal_fetcher_test_dynamoDB/provider.py
opal_fetcher_test_dynamodb-0.1.5.dist-info/LICENSE
opal_fetcher_test_dynamodb-0.1.5.dist-info/METADATA
opal_fetcher_test_dynamodb-0.1.5.dist-info/WHEEL
opal_fetcher_test_dynamodb-0.1.5.dist-info/top_level.txt
opal_fetcher_test_dynamodb-0.1.5.dist-info/RECORD
