Metadata-Version: 2.1
Name: opal-fetcher-test-dynamodb
Version: 0.1.5
Summary: A short description of your package
Author-email: Your Name <your.email@example.com>
License: Apache License
Project-URL: Homepage, https://github.com/rrrJiia/opal-fetcher-test-dynamoDB
Classifier: Programming Language :: Python :: 3
Classifier: License :: OSI Approved :: MIT License
Classifier: Operating System :: OS Independent
Requires-Python: >=3.6
License-File: LICENSE
Requires-Dist: boto3
Requires-Dist: opal-common
Requires-Dist: cachetools
Requires-Dist: pydantic
Requires-Dist: flask
Requires-Dist: redis
